distru
